LICENSE
README.md
setup.cfg
setup.py
notificationmethods/__init__.py
notificationmethods/email.py
notificationmethods/notificacion.py
notificationspackageke.egg-info/PKG-INFO
notificationspackageke.egg-info/SOURCES.txt
notificationspackageke.egg-info/dependency_links.txt
notificationspackageke.egg-info/top_level.txt