Metadata-Version: 2.1
Name: notificationspackageke
Version: 0.1.7
Summary: Paquete de notificaciones
Home-page: https://github.com/Kemok-Repos/notification-service
Author: Carlos Pacheco
Author-email: carlos.pacheco@kemok.io
License: MIT
Platform: UNKNOWN
License-File: LICENSE
